stestr/__init__.py
stestr/__main__.py
stestr/bisect_tests.py
stestr/cli.py
stestr/colorizer.py
stestr/config_file.py
stestr/output.py
stestr/results.py
stestr/scheduler.py
stestr/selection.py
stestr/subunit_trace.py
stestr/test_processor.py
stestr/testlist.py
stestr/user_config.py
stestr/utils.py
stestr/version.py
stestr/commands/__init__.py
stestr/commands/failing.py
stestr/commands/history.py
stestr/commands/init.py
stestr/commands/last.py
stestr/commands/list.py
stestr/commands/load.py
stestr/commands/run.py
stestr/commands/slowest.py
stestr/repository/__init__.py
stestr/repository/abstract.py
stestr/repository/file.py
stestr/repository/memory.py
stestr/repository/util.py
stestr/subunit_runner/__init__.py
stestr/subunit_runner/program.py
stestr/subunit_runner/run.py
stestr/tests/__init__.py
stestr/tests/base.py
stestr/tests/test_bisect_return_codes.py
stestr/tests/test_bisect_tests.py
stestr/tests/test_config_file.py
stestr/tests/test_load.py
stestr/tests/test_output.py
stestr/tests/test_return_codes.py
stestr/tests/test_run.py
stestr/tests/test_scheduler.py
stestr/tests/test_selection.py
stestr/tests/test_slowest.py
stestr/tests/test_subunit_trace.py
stestr/tests/test_test_processor.py
stestr/tests/test_user_config.py
stestr/tests/test_user_config_return_codes.py
stestr/tests/test_utils.py
stestr/tests/files/__init__.py
stestr/tests/files/bisect-fail-serial-tests
stestr/tests/files/failing-tests
stestr/tests/files/passing-tests
stestr/tests/files/setup.cfg
stestr/tests/files/stestr.yaml
stestr/tests/files/testr-conf
stestr/tests/files/tox.ini
stestr/tests/repository/__init__.py
stestr/tests/repository/test_file.py
stestr/tests/repository/test_util.py
stestr/tests/sample_streams/all_skips.subunit
stestr/tests/sample_streams/failure.subunit
stestr/tests/sample_streams/successful.subunit
stestr-4.1.0.dist-info/AUTHORS
stestr-4.1.0.dist-info/LICENSE
stestr-4.1.0.dist-info/METADATA
stestr-4.1.0.dist-info/WHEEL
stestr-4.1.0.dist-info/entry_points.txt
stestr-4.1.0.dist-info/pbr.json
stestr-4.1.0.dist-info/top_level.txt
stestr-4.1.0.dist-info/RECORD
