Metadata-Version: 2.1
Name: stestr
Version: 4.1.0
Summary: A parallel Python test runner built around subunit
Home-page: http://stestr.readthedocs.io/en/latest/
Author: Matthew Treinish
Author-email: mtreinish@kortar.org
License: Apache-2.0
Project-URL: Documentation, https://stestr.readthedocs.io
Project-URL: Source Code, https://github.com/mtreinish/stestr
Project-URL: Bug Tracker, https://github.com/mtreinish/stestr/issues
Platform: UNKNOWN
Classifier: Intended Audience :: Information Technology
Classifier: Intended Audience :: System Administrators
Classifier: Intended Audience :: Developers
Classifier: License :: OSI Approved :: Apache Software License
Classifier: Operating System :: OS Independent
Classifier: Programming Language :: Python
Classifier: Programming Language :: Python :: 3
Classifier: Programming Language :: Python :: 3.7
Classifier: Programming Language :: Python :: 3.8
Classifier: Programming Language :: Python :: 3.9
Classifier: Programming Language :: Python :: 3.10
Classifier: Programming Language :: Python :: 3.11
Classifier: Topic :: Software Development :: Testing
Classifier: Topic :: Software Development :: Quality Assurance
Requires-Python: >=3.6
Provides-Extra: sql
Provides-Extra: test
